qdatamatrix/__init__.py
qdatamatrix/_qcell.py
qdatamatrix/_qcelldelegate.py
qdatamatrix/_qcontextmenu.py
qdatamatrix/_qdatamatrix.py
qdatamatrix/_qspreadsheet.py
qdatamatrix/_version.py
qdatamatrix/decorators.py
qdatamatrix/translate.py
python_qdatamatrix-0.1.31.dist-info/METADATA
python_qdatamatrix-0.1.31.dist-info/WHEEL
python_qdatamatrix-0.1.31.dist-info/top_level.txt
python_qdatamatrix-0.1.31.dist-info/RECORD
