Metadata-Version: 2.1
Name: python-qdatamatrix
Version: 0.1.31
Summary: A PyQt4/PyQt5 widget for viewing and editing a DataMatrix object
Home-page: https://github.com/smathot/python-qdatamatrix
Author: Sebastiaan Mathot
Author-email: s.mathot@cogsci.nl
License: GNU GPL Version 3
Platform: UNKNOWN
Classifier: Development Status :: 4 - Beta
Classifier: Intended Audience :: Science/Research
Classifier: Topic :: Scientific/Engineering
Classifier: License :: OSI Approved :: GNU General Public License v3 (GPLv3)
Classifier: Programming Language :: Python :: 2
Classifier: Programming Language :: Python :: 3
Requires-Dist: python-datamatrix
